prepic/__init__.py
prepic/base.py
prepic/constants.py
prepic/ionization.py
prepic/laser.py
prepic/lwfa.py
prepic/plasma.py
prepic/radiation.py
prepic/simulation.py
prepic/util.py
prepic-0.2.5.dist-info/AUTHORS.rst
prepic-0.2.5.dist-info/LICENSE
prepic-0.2.5.dist-info/METADATA
prepic-0.2.5.dist-info/WHEEL
prepic-0.2.5.dist-info/top_level.txt
prepic-0.2.5.dist-info/RECORD
