Metadata-Version: 2.1
Name: prepic
Version: 0.2.5
Summary: analytically estimate various laser-plasma parameters for experiments and PIC simulations
Home-page: https://github.com/berceanu/prepic
Author: Andrei Berceanu
Author-email: andreicberceanu@gmail.com
License: BSD license
Keywords: prepic
Classifier: Development Status :: 2 - Pre-Alpha
Classifier: Intended Audience :: Science/Research
Classifier: License :: OSI Approved :: BSD License
Classifier: Natural Language :: English
Classifier: Topic :: Scientific/Engineering :: Physics
Classifier: Programming Language :: Python :: 3.6
Requires-Python: >= 3.6
License-File: LICENSE
License-File: AUTHORS.rst
Requires-Dist: unyt (>=2.3.1)
Requires-Dist: numpy (>=1.16.1)
Requires-Dist: scipy (>=1.3.1)
Requires-Dist: matplotlib (>=3.1.0)
Requires-Dist: sliceplots (>=0.3.1)
